crownstone_core/Constants.py
crownstone_core/Enums.py
crownstone_core/Exceptions.py
crownstone_core/__init__.py
crownstone_core/core/__init__.py
crownstone_core/core/modules/EncryptionSettings.py
crownstone_core/core/modules/__init__.py
crownstone_core/packets/Advertisement.py
crownstone_core/packets/BasePacket.py
crownstone_core/packets/MicroappPacket.py
crownstone_core/packets/ResultPacket.py
crownstone_core/packets/ServiceData.py
crownstone_core/packets/SessionDataPacket.py
crownstone_core/packets/__init__.py
crownstone_core/packets/assetFilter/AssetFilterPackets.py
crownstone_core/packets/assetFilter/CuckooFilterPackets.py
crownstone_core/packets/assetFilter/ExactMatchFilter.py
crownstone_core/packets/assetFilter/FilterCommandPackets.py
crownstone_core/packets/assetFilter/FilterDataPackets.py
crownstone_core/packets/assetFilter/FilterMetaDataPackets.py
crownstone_core/packets/assetFilter/FilterOutputPackets.py
crownstone_core/packets/assetFilter/InputDescriptionPackets.py
crownstone_core/packets/assetFilter/__init__.py
crownstone_core/packets/assetFilter/builders/AssetFilter.py
crownstone_core/packets/assetFilter/builders/AssetIdSourceBuilder.py
crownstone_core/packets/assetFilter/builders/__init__.py
crownstone_core/packets/assetFilter/util/AssetFilterChunker.py
crownstone_core/packets/assetFilter/util/AssetFilterMasterCrc.py
crownstone_core/packets/assetFilter/util/AssetFilterSyncer.py
crownstone_core/packets/assetFilter/util/__init__.py
crownstone_core/packets/behaviour/ActiveDays.py
crownstone_core/packets/behaviour/BehaviourBase.py
crownstone_core/packets/behaviour/BehaviourParser.py
crownstone_core/packets/behaviour/BehaviourTypes.py
crownstone_core/packets/behaviour/ExtendedSwitchBehaviour.py
crownstone_core/packets/behaviour/PresenceDescription.py
crownstone_core/packets/behaviour/SwitchBehaviour.py
crownstone_core/packets/behaviour/TimeDescription.py
crownstone_core/packets/behaviour/TwilightBehaviour.py
crownstone_core/packets/behaviour/__init__.py
crownstone_core-3.2.0.dist-info/LICENSE-APACHE
crownstone_core-3.2.0.dist-info/LICENSE-LGPL
crownstone_core-3.2.0.dist-info/LICENSE-MIT
crownstone_core-3.2.0.dist-info/METADATA
crownstone_core-3.2.0.dist-info/WHEEL
crownstone_core-3.2.0.dist-info/top_level.txt
crownstone_core-3.2.0.dist-info/RECORD
