Metadata-Version: 2.1
Name: crownstone-core
Version: 3.2.0
Summary: UNKNOWN
Home-page: https://github.com/crownstone/crownstone-lib-python-core
Author: Crownstone B.V.
License: UNKNOWN
Platform: UNKNOWN
Classifier: Programming Language :: Python :: 3.7
Requires-Python: >=3.7
Requires-Dist: pyaes (~=1.6)
